shelvecache/__init__.py
shelvecache/shelvecache.py
shelve_cache-0.0.4.dist-info/LICENSE
shelve_cache-0.0.4.dist-info/METADATA
shelve_cache-0.0.4.dist-info/WHEEL
shelve_cache-0.0.4.dist-info/top_level.txt
shelve_cache-0.0.4.dist-info/RECORD
