Metadata-Version: 2.1
Name: shelve_cache
Version: 0.0.4
Summary: Persistant decorator
Author: Sanchit Singh
Author-email: <sanchitsingh849@gmail.com>
Keywords: python,cache,shelve,decorator,sockets
Classifier: Development Status :: 1 - Planning
Classifier: Intended Audience :: Developers
Classifier: Programming Language :: Python :: 3
Classifier: Operating System :: Unix
Classifier: Operating System :: MacOS :: MacOS X
Classifier: Operating System :: Microsoft :: Windows
License-File: LICENSE
